{
 "agency": "Bronx Borough President",
 "collection": "CommunityBoardAppointment",
 "schema": "https://raw.githubusercontent.com/api-evangelist/nyc/main/bronxbp/schemas/community-board-appointment.json",
 "count": 2,
 "example": true,
 "data": [
  {
   "communityBoard": {
    "communityBoard": "example communityBoard",
    "name": "Example name"
   },
   "firstName": "Example firstName 1",
   "lastName": "Example lastName",
   "recommendingOfficial": "example recommendingOfficial",
   "termExpires": "example termExpires",
   "year": "example year",
   "applicationZipCode": "10007"
  },
  {
   "communityBoard": {
    "communityBoard": "example communityBoard",
    "name": "Example name"
   },
   "firstName": "Example firstName 2",
   "lastName": "Example lastName",
   "recommendingOfficial": "example recommendingOfficial",
   "termExpires": "example termExpires",
   "year": "example year",
   "applicationZipCode": "10007"
  }
 ]
}